clavier/__init__.py
clavier/arg_par.py
clavier/dyn.py
clavier/err.py
clavier/io.py
clavier/rich_fmt.py
clavier/sesh.py
clavier/sh.py
clavier/txt.py
clavier/cfg/__init__.py
clavier/cfg/changeset.py
clavier/cfg/config.py
clavier/cfg/key.py
clavier/cfg/scope.py
clavier/etc/__init__.py
clavier/etc/ins.py
clavier/etc/iter.py
clavier/etc/type.py
clavier/log/__init__.py
clavier/log/kwds_logger.py
clavier/log/log_getter.py
clavier/log/rich_handler.py
clavier-0.1.2.dist-info/LICENSE
clavier-0.1.2.dist-info/METADATA
clavier-0.1.2.dist-info/WHEEL
clavier-0.1.2.dist-info/top_level.txt
clavier-0.1.2.dist-info/RECORD
